simple-lda/__init__.py
simple-lda/lda_training.py
simple-lda/my_lda_training.py
simple-lda/my_stemming_algo.py
simple-lda/my_stop_words.py
simple-lda/my_tokenize.py
simple_lda-0.2.0.dist-info/DESCRIPTION.rst
simple_lda-0.2.0.dist-info/METADATA
simple_lda-0.2.0.dist-info/RECORD
simple_lda-0.2.0.dist-info/WHEEL
simple_lda-0.2.0.dist-info/metadata.json
simple_lda-0.2.0.dist-info/top_level.txt
tests/__init__.py
tests/test_lda.py
