Metadata-Version: 2.0
Name: simple-lda
Version: 0.2.0
Summary: Python library for Latent Dirichlet allocation (lda)
Home-page: https://github.com/Sylhare/simple-lda
Author: sylhare
Author-email: sylhare@outlook.com
License: Apache License 2.0
Platform: any
Classifier: Development Status :: 2 - Pre-Alpha
Classifier: Programming Language :: Python
Classifier: Programming Language :: Python :: 3.5
Classifier: Environment :: Other Environment
Classifier: Intended Audience :: Science/Research
Classifier: Intended Audience :: Education
Classifier: Natural Language :: English
Classifier: License :: OSI Approved :: Apache Software License
Classifier: Operating System :: OS Independent
Classifier: Topic :: Software Development :: Libraries
Classifier: Topic :: Software Development :: Libraries :: Python Modules
Classifier: Topic :: Text Processing
Classifier: Topic :: Utilities
